{
  "anime_name": "Classicaloid 2",
  "anime_url": "https://hianime.ad/anime/classicaloid-2",
  "slug": "classicaloid-2",
  "mal_id": 35334,
  "total_episodes": 25,
  "captured_at": "2026-06-03T06:07:20",
  "source": "hianime.ad",
  "episodes": [
    {
      "episode_title": "Hippo and Little Brother and Otowa Mansion",
      "episode_url": "https://hianime.ad/watch/classicaloid-2/ep-1",
      "sub": {
        "HD-1": {
          "35334-malep-1_vibeplayer_sub": "https://vibeplayer.site/d16042b3996b44d7",
          "35334-malep-1_vibeplayer_sub_m3u8": "https://vibeplayer.site/public/stream/d16042b3996b44d7/master.m3u8"
        },
        "HD-2": {
          "35334-malep-1_vibeplayer_sub": "https://vibeplayer.site/aga035e99b3c208afe4c7d1186267a1ba94h",
          "35334-malep-1_vibeplayer_sub_m3u8": null
        },
        "Earnvids": {
          "35334-malep-1_otakuvid_sub": "https://otakuvid.online/embed/uox0jxl6ldb2",
          "35334-malep-1_otakuvid_sub_m3u8": null
        }
      },
      "dub": {},
      "hsub": {
        "HD-1": {
          "35334-malep-1_vibeplayer_hsub": "https://vibeplayer.site/4fba5a3a84d32acd",
          "35334-malep-1_vibeplayer_hsub_m3u8": "https://vibeplayer.site/public/stream/4fba5a3a84d32acd/master.m3u8"
        },
        "HD-2": {
          "35334-malep-1_vibeplayer_hsub": "https://vibeplayer.site/agbc8be17eb741cfb24fc0c63e000574ec4h",
          "35334-malep-1_vibeplayer_hsub_m3u8": null
        },
        "Earnvids": {
          "35334-malep-1_otakuvid_hsub": "https://otakuvid.online/embed/7irdnu3jdw7j",
          "35334-malep-1_otakuvid_hsub_m3u8": null
        },
        "Doodstream": {
          "35334-malep-1_playmogo_hsub": "https://playmogo.com/e/my95f8mhg09s",
          "35334-malep-1_playmogo_hsub_m3u8": null
        }
      }
    },
    {
      "episode_title": "My Little Brother",
      "episode_url": "https://hianime.ad/watch/classicaloid-2/ep-2",
      "sub": {
        "HD-1": {
          "35334-malep-2_vibeplayer_sub": "https://vibeplayer.site/614b8c64c0b2757d",
          "35334-malep-2_vibeplayer_sub_m3u8": "https://vibeplayer.site/public/stream/614b8c64c0b2757d/master.m3u8"
        },
        "HD-2": {
          "35334-malep-2_vibeplayer_sub": "https://vibeplayer.site/ag2462f6023fefa5accc53ed5b2b86f4f74h",
          "35334-malep-2_vibeplayer_sub_m3u8": null
        },
        "Earnvids": {
          "35334-malep-2_otakuvid_sub": "https://otakuvid.online/embed/mp7yflxfwq09",
          "35334-malep-2_otakuvid_sub_m3u8": null
        }
      },
      "dub": {},
      "hsub": {
        "HD-1": {
          "35334-malep-2_vibeplayer_hsub": "https://vibeplayer.site/1260ef8ed8b17554",
          "35334-malep-2_vibeplayer_hsub_m3u8": "https://vibeplayer.site/public/stream/1260ef8ed8b17554/master.m3u8"
        },
        "HD-2": {
          "35334-malep-2_vibeplayer_hsub": "https://vibeplayer.site/ag2329b5c54059548fa4889d9b17e3c9334h",
          "35334-malep-2_vibeplayer_hsub_m3u8": null
        },
        "Earnvids": {
          "35334-malep-2_otakuvid_hsub": "https://otakuvid.online/embed/4oy0vxw6rhzi",
          "35334-malep-2_otakuvid_hsub_m3u8": null
        },
        "Doodstream": {
          "35334-malep-2_playmogo_hsub": "https://playmogo.com/e/0bfpv95luzl1",
          "35334-malep-2_playmogo_hsub_m3u8": null
        }
      }
    },
    {
      "episode_title": "Ever Since the Day We First Met",
      "episode_url": "https://hianime.ad/watch/classicaloid-2/ep-3",
      "sub": {
        "HD-1": {
          "35334-malep-3_vibeplayer_sub": "https://vibeplayer.site/f649d3e380785c1e",
          "35334-malep-3_vibeplayer_sub_m3u8": "https://vibeplayer.site/public/stream/f649d3e380785c1e/master.m3u8"
        },
        "HD-2": {
          "35334-malep-3_vibeplayer_sub": "https://vibeplayer.site/ag79f1629f642122b5ddde96f83b32cef24h",
          "35334-malep-3_vibeplayer_sub_m3u8": null
        },
        "Earnvids": {
          "35334-malep-3_otakuvid_sub": "https://otakuvid.online/embed/vqetywrd2uht",
          "35334-malep-3_otakuvid_sub_m3u8": null
        }
      },
      "dub": {},
      "hsub": {
        "HD-1": {
          "35334-malep-3_vibeplayer_hsub": "https://vibeplayer.site/4776113b1e771e18",
          "35334-malep-3_vibeplayer_hsub_m3u8": "https://vibeplayer.site/public/stream/4776113b1e771e18/master.m3u8"
        },
        "HD-2": {
          "35334-malep-3_vibeplayer_hsub": "https://vibeplayer.site/agc789c00825e93e05384533125cba94e84h",
          "35334-malep-3_vibeplayer_hsub_m3u8": null
        },
        "Earnvids": {
          "35334-malep-3_otakuvid_hsub": "https://otakuvid.online/embed/e07vcox1iec4",
          "35334-malep-3_otakuvid_hsub_m3u8": null
        },
        "Doodstream": {
          "35334-malep-3_playmogo_hsub": "https://playmogo.com/e/y619hknpi065",
          "35334-malep-3_playmogo_hsub_m3u8": null
        }
      }
    },
    {
      "episode_title": "Fever! Let's Pugi",
      "episode_url": "https://hianime.ad/watch/classicaloid-2/ep-4",
      "sub": {
        "HD-1": {
          "35334-malep-4_vibeplayer_sub": "https://vibeplayer.site/1e5200b444335fac",
          "35334-malep-4_vibeplayer_sub_m3u8": "https://vibeplayer.site/public/stream/1e5200b444335fac/master.m3u8"
        },
        "HD-2": {
          "35334-malep-4_vibeplayer_sub": "https://vibeplayer.site/ag38c86cc2736b5387b548a752723146164h",
          "35334-malep-4_vibeplayer_sub_m3u8": null
        },
        "Earnvids": {
          "35334-malep-4_otakuvid_sub": "https://otakuvid.online/embed/bgq5l49aogiu",
          "35334-malep-4_otakuvid_sub_m3u8": null
        }
      },
      "dub": {},
      "hsub": {
        "HD-1": {
          "35334-malep-4_vibeplayer_hsub": "https://vibeplayer.site/3dd316de57a51c32",
          "35334-malep-4_vibeplayer_hsub_m3u8": "https://vibeplayer.site/public/stream/3dd316de57a51c32/master.m3u8"
        },
        "HD-2": {
          "35334-malep-4_vibeplayer_hsub": "https://vibeplayer.site/ag6bc61621563312d80479904d0bf268fd4h",
          "35334-malep-4_vibeplayer_hsub_m3u8": null
        },
        "Earnvids": {
          "35334-malep-4_otakuvid_hsub": "https://otakuvid.online/embed/26x0b3j6z81q",
          "35334-malep-4_otakuvid_hsub_m3u8": null
        },
        "Doodstream": {
          "35334-malep-4_playmogo_hsub": "https://playmogo.com/e/cdgyxvtyp5kr",
          "35334-malep-4_playmogo_hsub_m3u8": null
        }
      }
    },
    {
      "episode_title": "A Great Man",
      "episode_url": "https://hianime.ad/watch/classicaloid-2/ep-5",
      "sub": {
        "HD-1": {
          "35334-malep-5_vibeplayer_sub": "https://vibeplayer.site/161aff6173d3eb36",
          "35334-malep-5_vibeplayer_sub_m3u8": "https://vibeplayer.site/public/stream/161aff6173d3eb36/master.m3u8"
        },
        "HD-2": {
          "35334-malep-5_vibeplayer_sub": "https://vibeplayer.site/ag0ed2c21b3a862dbf38f800156f4d76804h",
          "35334-malep-5_vibeplayer_sub_m3u8": null
        },
        "Earnvids": {
          "35334-malep-5_otakuvid_sub": "https://otakuvid.online/embed/l9x91tverpw4",
          "35334-malep-5_otakuvid_sub_m3u8": null
        }
      },
      "dub": {},
      "hsub": {
        "HD-1": {
          "35334-malep-5_vibeplayer_hsub": "https://vibeplayer.site/4f71e25dbdddaa3b",
          "35334-malep-5_vibeplayer_hsub_m3u8": "https://vibeplayer.site/public/stream/4f71e25dbdddaa3b/master.m3u8"
        },
        "HD-2": {
          "35334-malep-5_vibeplayer_hsub": "https://vibeplayer.site/ag5d612e13528f8e2fd5fa28c61f9970c54h",
          "35334-malep-5_vibeplayer_hsub_m3u8": null
        },
        "Earnvids": {
          "35334-malep-5_otakuvid_hsub": "https://otakuvid.online/embed/ker5irale1k3",
          "35334-malep-5_otakuvid_hsub_m3u8": null
        },
        "Doodstream": {
          "35334-malep-5_playmogo_hsub": "https://playmogo.com/e/s44d00mmnl6l",
          "35334-malep-5_playmogo_hsub_m3u8": null
        }
      }
    },
    {
      "episode_title": "Mother Provides the Crab, Hippo Becomes a Rhino",
      "episode_url": "https://hianime.ad/watch/classicaloid-2/ep-6",
      "sub": {
        "HD-1": {
          "35334-malep-6_vibeplayer_sub": "https://vibeplayer.site/60e1d824e463595c",
          "35334-malep-6_vibeplayer_sub_m3u8": "https://vibeplayer.site/public/stream/60e1d824e463595c/master.m3u8"
        },
        "HD-2": {
          "35334-malep-6_vibeplayer_sub": "https://vibeplayer.site/agdad5838d130e5eb9676336cbfc22ece54h",
          "35334-malep-6_vibeplayer_sub_m3u8": null
        },
        "Earnvids": {
          "35334-malep-6_otakuvid_sub": "https://otakuvid.online/embed/wijd6530avx5",
          "35334-malep-6_otakuvid_sub_m3u8": null
        }
      },
      "dub": {},
      "hsub": {
        "HD-1": {
          "35334-malep-6_vibeplayer_hsub": "https://vibeplayer.site/34e20d9551ca7d7f",
          "35334-malep-6_vibeplayer_hsub_m3u8": "https://vibeplayer.site/public/stream/34e20d9551ca7d7f/master.m3u8"
        },
        "HD-2": {
          "35334-malep-6_vibeplayer_hsub": "https://vibeplayer.site/ag81ba02777427b09a09494b7dc31c5a134h",
          "35334-malep-6_vibeplayer_hsub_m3u8": null
        },
        "Earnvids": {
          "35334-malep-6_otakuvid_hsub": "https://otakuvid.online/embed/0h5htbzxchl8",
          "35334-malep-6_otakuvid_hsub_m3u8": null
        },
        "Doodstream": {
          "35334-malep-6_playmogo_hsub": "https://playmogo.com/e/t98o81yr60zx",
          "35334-malep-6_playmogo_hsub_m3u8": null
        }
      }
    },
    {
      "episode_title": "Looking for a Husband for Kanae",
      "episode_url": "https://hianime.ad/watch/classicaloid-2/ep-7",
      "sub": {
        "HD-1": {
          "35334-malep-7_vibeplayer_sub": "https://vibeplayer.site/24716686c670671b",
          "35334-malep-7_vibeplayer_sub_m3u8": "https://vibeplayer.site/public/stream/24716686c670671b/master.m3u8"
        },
        "HD-2": {
          "35334-malep-7_vibeplayer_sub": "https://vibeplayer.site/age2bd3b5c631984e17659b6b8fad60dee4h",
          "35334-malep-7_vibeplayer_sub_m3u8": null
        },
        "Earnvids": {
          "35334-malep-7_otakuvid_sub": "https://otakuvid.online/embed/570iyferkfy8",
          "35334-malep-7_otakuvid_sub_m3u8": null
        }
      },
      "dub": {},
      "hsub": {
        "HD-1": {
          "35334-malep-7_vibeplayer_hsub": "https://vibeplayer.site/5a3d58e6c5ddeea8",
          "35334-malep-7_vibeplayer_hsub_m3u8": "https://vibeplayer.site/public/stream/5a3d58e6c5ddeea8/master.m3u8"
        },
        "HD-2": {
          "35334-malep-7_vibeplayer_hsub": "https://vibeplayer.site/age452e1a79ea35c9a7d521a60f93d11644h",
          "35334-malep-7_vibeplayer_hsub_m3u8": null
        },
        "Earnvids": {
          "35334-malep-7_otakuvid_hsub": "https://otakuvid.online/embed/73mcydg286ph",
          "35334-malep-7_otakuvid_hsub_m3u8": null
        },
        "Doodstream": {
          "35334-malep-7_playmogo_hsub": "https://playmogo.com/e/tckkh53b7gy4",
          "35334-malep-7_playmogo_hsub_m3u8": null
        }
      }
    },
    {
      "episode_title": "To Be Motz Is to Fib",
      "episode_url": "https://hianime.ad/watch/classicaloid-2/ep-8",
      "sub": {
        "HD-1": {
          "35334-malep-8_vibeplayer_sub": "https://vibeplayer.site/9aff428d52609147",
          "35334-malep-8_vibeplayer_sub_m3u8": "https://vibeplayer.site/public/stream/9aff428d52609147/master.m3u8"
        },
        "HD-2": {
          "35334-malep-8_vibeplayer_sub": "https://vibeplayer.site/ag7b3707986f49abddd418ba9041a1c5314h",
          "35334-malep-8_vibeplayer_sub_m3u8": null
        },
        "Earnvids": {
          "35334-malep-8_otakuvid_sub": "https://otakuvid.online/embed/l04aq1obmxw8",
          "35334-malep-8_otakuvid_sub_m3u8": null
        }
      },
      "dub": {},
      "hsub": {
        "HD-1": {
          "35334-malep-8_vibeplayer_hsub": "https://vibeplayer.site/93e89c06921f4251",
          "35334-malep-8_vibeplayer_hsub_m3u8": "https://vibeplayer.site/public/stream/93e89c06921f4251/master.m3u8"
        },
        "HD-2": {
          "35334-malep-8_vibeplayer_hsub": "https://vibeplayer.site/agec8f03b8dc2d8477a4d25ed9ab38d6584h",
          "35334-malep-8_vibeplayer_hsub_m3u8": null
        },
        "Earnvids": {
          "35334-malep-8_otakuvid_hsub": "https://otakuvid.online/embed/lhvmw3fk4yby",
          "35334-malep-8_otakuvid_hsub_m3u8": null
        },
        "Doodstream": {
          "35334-malep-8_playmogo_hsub": "https://playmogo.com/e/a5jpomoub1qx",
          "35334-malep-8_playmogo_hsub_m3u8": null
        }
      }
    },
    {
      "episode_title": "A World Without Circles",
      "episode_url": "https://hianime.ad/watch/classicaloid-2/ep-9",
      "sub": {
        "HD-1": {
          "35334-malep-9_vibeplayer_sub": "https://vibeplayer.site/936868b9d3219321",
          "35334-malep-9_vibeplayer_sub_m3u8": "https://vibeplayer.site/public/stream/936868b9d3219321/master.m3u8"
        },
        "HD-2": {
          "35334-malep-9_vibeplayer_sub": "https://vibeplayer.site/ag5015eee246c31675e2e9597a5dc18bd04h",
          "35334-malep-9_vibeplayer_sub_m3u8": null
        },
        "Earnvids": {
          "35334-malep-9_otakuvid_sub": "https://otakuvid.online/embed/p19u8qb44en1",
          "35334-malep-9_otakuvid_sub_m3u8": null
        }
      },
      "dub": {},
      "hsub": {
        "HD-1": {
          "35334-malep-9_vibeplayer_hsub": "https://vibeplayer.site/e1a47eb95dd26dbb",
          "35334-malep-9_vibeplayer_hsub_m3u8": "https://vibeplayer.site/public/stream/e1a47eb95dd26dbb/master.m3u8"
        },
        "HD-2": {
          "35334-malep-9_vibeplayer_hsub": "https://vibeplayer.site/ag993b0ea61703ed5521ad880a7f32cd974h",
          "35334-malep-9_vibeplayer_hsub_m3u8": null
        },
        "Earnvids": {
          "35334-malep-9_otakuvid_hsub": "https://otakuvid.online/embed/rqdaiyc7puot",
          "35334-malep-9_otakuvid_hsub_m3u8": null
        },
        "Doodstream": {
          "35334-malep-9_playmogo_hsub": "https://playmogo.com/e/7v8xmne6fixc",
          "35334-malep-9_playmogo_hsub_m3u8": null
        }
      }
    },
    {
      "episode_title": "Liszt vs Risuto: Bell (Gong) of Destiny",
      "episode_url": "https://hianime.ad/watch/classicaloid-2/ep-10",
      "sub": {
        "HD-1": {
          "35334-malep-10_vibeplayer_sub": "https://vibeplayer.site/012568a60aa69979",
          "35334-malep-10_vibeplayer_sub_m3u8": "https://vibeplayer.site/public/stream/012568a60aa69979/master.m3u8"
        },
        "HD-2": {
          "35334-malep-10_vibeplayer_sub": "https://vibeplayer.site/ag389866685d9f6ef2bd1f33f7d9a6d37b4h",
          "35334-malep-10_vibeplayer_sub_m3u8": null
        },
        "Earnvids": {
          "35334-malep-10_otakuvid_sub": "https://otakuvid.online/embed/gjf4cvucw270",
          "35334-malep-10_otakuvid_sub_m3u8": null
        }
      },
      "dub": {},
      "hsub": {
        "HD-1": {
          "35334-malep-10_vibeplayer_hsub": "https://vibeplayer.site/ab9b526c793431c8",
          "35334-malep-10_vibeplayer_hsub_m3u8": "https://vibeplayer.site/public/stream/ab9b526c793431c8/master.m3u8"
        },
        "HD-2": {
          "35334-malep-10_vibeplayer_hsub": "https://vibeplayer.site/agbdbfa8a345c1a71fa36e79dc6dc24b0e4h",
          "35334-malep-10_vibeplayer_hsub_m3u8": null
        },
        "Earnvids": {
          "35334-malep-10_otakuvid_hsub": "https://otakuvid.online/embed/brfqfza87pch",
          "35334-malep-10_otakuvid_hsub_m3u8": null
        },
        "Doodstream": {
          "35334-malep-10_playmogo_hsub": "https://playmogo.com/e/yr6f1cprjhfb",
          "35334-malep-10_playmogo_hsub_m3u8": null
        }
      }
    },
    {
      "episode_title": "Nothing But Saltiness",
      "episode_url": "https://hianime.ad/watch/classicaloid-2/ep-11",
      "sub": {
        "HD-1": {
          "35334-malep-11_vibeplayer_sub": "https://vibeplayer.site/f1b947db60921268",
          "35334-malep-11_vibeplayer_sub_m3u8": "https://vibeplayer.site/public/stream/f1b947db60921268/master.m3u8"
        },
        "HD-2": {
          "35334-malep-11_vibeplayer_sub": "https://vibeplayer.site/ag566e4faec7b97f3c46d74860f9deb1194h",
          "35334-malep-11_vibeplayer_sub_m3u8": null
        },
        "Earnvids": {
          "35334-malep-11_otakuvid_sub": "https://otakuvid.online/embed/4lpjkqq8h4vu",
          "35334-malep-11_otakuvid_sub_m3u8": null
        }
      },
      "dub": {},
      "hsub": {
        "HD-1": {
          "35334-malep-11_vibeplayer_hsub": "https://vibeplayer.site/1eed5dcde50a51eb",
          "35334-malep-11_vibeplayer_hsub_m3u8": "https://vibeplayer.site/public/stream/1eed5dcde50a51eb/master.m3u8"
        },
        "HD-2": {
          "35334-malep-11_vibeplayer_hsub": "https://vibeplayer.site/ag30bca6ed4fbe0295be888e0238c9783b4h",
          "35334-malep-11_vibeplayer_hsub_m3u8": null
        },
        "Earnvids": {
          "35334-malep-11_otakuvid_hsub": "https://otakuvid.online/embed/o4y25lqtjqwh",
          "35334-malep-11_otakuvid_hsub_m3u8": null
        },
        "Doodstream": {
          "35334-malep-11_playmogo_hsub": "https://playmogo.com/e/3e68mpfomlne",
          "35334-malep-11_playmogo_hsub_m3u8": null
        }
      }
    },
    {
      "episode_title": "Wagner's Ambition",
      "episode_url": "https://hianime.ad/watch/classicaloid-2/ep-12",
      "sub": {
        "HD-1": {
          "35334-malep-12_vibeplayer_sub": "https://vibeplayer.site/e26c56a829fd0ce2",
          "35334-malep-12_vibeplayer_sub_m3u8": "https://vibeplayer.site/public/stream/e26c56a829fd0ce2/master.m3u8"
        },
        "HD-2": {
          "35334-malep-12_vibeplayer_sub": "https://vibeplayer.site/ag3c281f894cfde6a21e3d2d7d5fb59b6b4h",
          "35334-malep-12_vibeplayer_sub_m3u8": null
        },
        "Earnvids": {
          "35334-malep-12_otakuvid_sub": "https://otakuvid.online/embed/pjrd3mpx1ai8",
          "35334-malep-12_otakuvid_sub_m3u8": null
        }
      },
      "dub": {},
      "hsub": {
        "HD-1": {
          "35334-malep-12_vibeplayer_hsub": "https://vibeplayer.site/24a221ea260fd510",
          "35334-malep-12_vibeplayer_hsub_m3u8": "https://vibeplayer.site/public/stream/24a221ea260fd510/master.m3u8"
        },
        "HD-2": {
          "35334-malep-12_vibeplayer_hsub": "https://vibeplayer.site/agba3f17b08930b2f302671af997c5af124h",
          "35334-malep-12_vibeplayer_hsub_m3u8": null
        },
        "Earnvids": {
          "35334-malep-12_otakuvid_hsub": "https://otakuvid.online/embed/59op75c1jo59",
          "35334-malep-12_otakuvid_hsub_m3u8": null
        },
        "Doodstream": {
          "35334-malep-12_playmogo_hsub": "https://playmogo.com/e/c0akq6uufpwq",
          "35334-malep-12_playmogo_hsub_m3u8": null
        }
      }
    },
    {
      "episode_title": "Forget the Year's Hardships! Red vs. White Musik Contest",
      "episode_url": "https://hianime.ad/watch/classicaloid-2/ep-13",
      "sub": {
        "HD-1": {
          "35334-malep-13_vibeplayer_sub": "https://vibeplayer.site/bde46b568a445f49",
          "35334-malep-13_vibeplayer_sub_m3u8": "https://vibeplayer.site/public/stream/bde46b568a445f49/master.m3u8"
        },
        "HD-2": {
          "35334-malep-13_vibeplayer_sub": "https://vibeplayer.site/agc7ae1abfed43b372b76bcd03f23714c54h",
          "35334-malep-13_vibeplayer_sub_m3u8": null
        },
        "Earnvids": {
          "35334-malep-13_otakuvid_sub": "https://otakuvid.online/embed/3n9sccl7uz3o",
          "35334-malep-13_otakuvid_sub_m3u8": null
        }
      },
      "dub": {},
      "hsub": {
        "HD-1": {
          "35334-malep-13_vibeplayer_hsub": "https://vibeplayer.site/c6086ea24ad91248",
          "35334-malep-13_vibeplayer_hsub_m3u8": "https://vibeplayer.site/public/stream/c6086ea24ad91248/master.m3u8"
        },
        "HD-2": {
          "35334-malep-13_vibeplayer_hsub": "https://vibeplayer.site/ag0ed2f001e624ef9ba41dee33f77d539d4h",
          "35334-malep-13_vibeplayer_hsub_m3u8": null
        },
        "Earnvids": {
          "35334-malep-13_otakuvid_hsub": "https://otakuvid.online/embed/lc9kjwopmv1x",
          "35334-malep-13_otakuvid_hsub_m3u8": null
        },
        "Doodstream": {
          "35334-malep-13_playmogo_hsub": "https://playmogo.com/e/z8ymkv3ge3i0",
          "35334-malep-13_playmogo_hsub_m3u8": null
        }
      }
    },
    {
      "episode_title": "Fall in Love, Pop Idol! Travel, Pygmy Hippo!",
      "episode_url": "https://hianime.ad/watch/classicaloid-2/ep-14",
      "sub": {
        "HD-1": {
          "35334-malep-14_vibeplayer_sub": "https://vibeplayer.site/402dbce714d88c42",
          "35334-malep-14_vibeplayer_sub_m3u8": "https://vibeplayer.site/public/stream/402dbce714d88c42/master.m3u8"
        },
        "HD-2": {
          "35334-malep-14_vibeplayer_sub": "https://vibeplayer.site/ag42eeb76cb92934cea4670350a953056c4h",
          "35334-malep-14_vibeplayer_sub_m3u8": null
        },
        "Earnvids": {
          "35334-malep-14_otakuvid_sub": "https://otakuvid.online/embed/bipdbh1vtvc5",
          "35334-malep-14_otakuvid_sub_m3u8": null
        }
      },
      "dub": {},
      "hsub": {
        "HD-1": {
          "35334-malep-14_vibeplayer_hsub": "https://vibeplayer.site/872113d42b64203b",
          "35334-malep-14_vibeplayer_hsub_m3u8": "https://vibeplayer.site/public/stream/872113d42b64203b/master.m3u8"
        },
        "HD-2": {
          "35334-malep-14_vibeplayer_hsub": "https://vibeplayer.site/agcc740de600824dde1d5f4ab57135c6574h",
          "35334-malep-14_vibeplayer_hsub_m3u8": null
        },
        "Earnvids": {
          "35334-malep-14_otakuvid_hsub": "https://otakuvid.online/embed/1kf647pe2f97",
          "35334-malep-14_otakuvid_hsub_m3u8": null
        },
        "Doodstream": {
          "35334-malep-14_playmogo_hsub": "https://playmogo.com/e/u31zl3y4c68y",
          "35334-malep-14_playmogo_hsub_m3u8": null
        }
      }
    },
    {
      "episode_title": "Dosukoi! Otowa Sumo Stable",
      "episode_url": "https://hianime.ad/watch/classicaloid-2/ep-15",
      "sub": {
        "HD-1": {
          "35334-malep-15_vibeplayer_sub": "https://vibeplayer.site/e20e138d600eed48",
          "35334-malep-15_vibeplayer_sub_m3u8": "https://vibeplayer.site/public/stream/e20e138d600eed48/master.m3u8"
        },
        "HD-2": {
          "35334-malep-15_vibeplayer_sub": "https://vibeplayer.site/agbe87aafa0540dcdbea6d689d625a82f14h",
          "35334-malep-15_vibeplayer_sub_m3u8": null
        },
        "Earnvids": {
          "35334-malep-15_otakuvid_sub": "https://otakuvid.online/embed/dl7sm8nlndev",
          "35334-malep-15_otakuvid_sub_m3u8": null
        }
      },
      "dub": {},
      "hsub": {
        "HD-1": {
          "35334-malep-15_vibeplayer_hsub": "https://vibeplayer.site/8f24aca23b84e91b",
          "35334-malep-15_vibeplayer_hsub_m3u8": "https://vibeplayer.site/public/stream/8f24aca23b84e91b/master.m3u8"
        },
        "HD-2": {
          "35334-malep-15_vibeplayer_hsub": "https://vibeplayer.site/agcc662b9d01d549a346da053e437392f04h",
          "35334-malep-15_vibeplayer_hsub_m3u8": null
        },
        "Earnvids": {
          "35334-malep-15_otakuvid_hsub": "https://otakuvid.online/embed/qtx3p88wf0aa",
          "35334-malep-15_otakuvid_hsub_m3u8": null
        },
        "Doodstream": {
          "35334-malep-15_playmogo_hsub": "https://playmogo.com/e/oqg82xjwk4qh",
          "35334-malep-15_playmogo_hsub_m3u8": null
        }
      }
    },
    {
      "episode_title": "A Reunion with the Great Unknown",
      "episode_url": "https://hianime.ad/watch/classicaloid-2/ep-16",
      "sub": {
        "HD-1": {
          "35334-malep-16_vibeplayer_sub": "https://vibeplayer.site/6e14e948854672a6",
          "35334-malep-16_vibeplayer_sub_m3u8": "https://vibeplayer.site/public/stream/6e14e948854672a6/master.m3u8"
        },
        "HD-2": {
          "35334-malep-16_vibeplayer_sub": "https://vibeplayer.site/ag4f3aa42a26cef7eebcbcd089770e09ae4h",
          "35334-malep-16_vibeplayer_sub_m3u8": null
        },
        "Earnvids": {
          "35334-malep-16_otakuvid_sub": "https://otakuvid.online/embed/ev0w95kkgy4c",
          "35334-malep-16_otakuvid_sub_m3u8": null
        }
      },
      "dub": {},
      "hsub": {
        "HD-1": {
          "35334-malep-16_vibeplayer_hsub": "https://vibeplayer.site/8e41b32d00099fbf",
          "35334-malep-16_vibeplayer_hsub_m3u8": "https://vibeplayer.site/public/stream/8e41b32d00099fbf/master.m3u8"
        },
        "HD-2": {
          "35334-malep-16_vibeplayer_hsub": "https://vibeplayer.site/ag6a51ed4a8dd2130e2e7bb298bc7fcd254h",
          "35334-malep-16_vibeplayer_hsub_m3u8": null
        },
        "Earnvids": {
          "35334-malep-16_otakuvid_hsub": "https://otakuvid.online/embed/ko2yidsyafqn",
          "35334-malep-16_otakuvid_hsub_m3u8": null
        },
        "Doodstream": {
          "35334-malep-16_playmogo_hsub": "https://playmogo.com/e/xvr0gfng3v6k",
          "35334-malep-16_playmogo_hsub_m3u8": null
        }
      }
    },
    {
      "episode_title": "WesternLoids of the Wild West",
      "episode_url": "https://hianime.ad/watch/classicaloid-2/ep-17",
      "sub": {
        "HD-1": {
          "35334-malep-17_vibeplayer_sub": "https://vibeplayer.site/bb8a00f7c3313d2d",
          "35334-malep-17_vibeplayer_sub_m3u8": "https://vibeplayer.site/public/stream/bb8a00f7c3313d2d/master.m3u8"
        },
        "HD-2": {
          "35334-malep-17_vibeplayer_sub": "https://vibeplayer.site/agd768624a8965ba14706ecd66bd311d014h",
          "35334-malep-17_vibeplayer_sub_m3u8": null
        },
        "Earnvids": {
          "35334-malep-17_otakuvid_sub": "https://otakuvid.online/embed/5ovb3taccjap",
          "35334-malep-17_otakuvid_sub_m3u8": null
        }
      },
      "dub": {},
      "hsub": {
        "HD-1": {
          "35334-malep-17_vibeplayer_hsub": "https://vibeplayer.site/390c055503325b98",
          "35334-malep-17_vibeplayer_hsub_m3u8": "https://vibeplayer.site/public/stream/390c055503325b98/master.m3u8"
        },
        "HD-2": {
          "35334-malep-17_vibeplayer_hsub": "https://vibeplayer.site/agc345e3e1ba5911226408f0b436dc5d7a4h",
          "35334-malep-17_vibeplayer_hsub_m3u8": null
        },
        "Earnvids": {
          "35334-malep-17_otakuvid_hsub": "https://otakuvid.online/embed/bt1qudjv85im",
          "35334-malep-17_otakuvid_hsub_m3u8": null
        },
        "Doodstream": {
          "35334-malep-17_playmogo_hsub": "https://playmogo.com/e/qk3fw1uuje00",
          "35334-malep-17_playmogo_hsub_m3u8": null
        }
      }
    },
    {
      "episode_title": "Goodbye, Big Sister",
      "episode_url": "https://hianime.ad/watch/classicaloid-2/ep-18",
      "sub": {
        "HD-1": {
          "35334-malep-18_vibeplayer_sub": "https://vibeplayer.site/7e513d48b7c91259",
          "35334-malep-18_vibeplayer_sub_m3u8": "https://vibeplayer.site/public/stream/7e513d48b7c91259/master.m3u8"
        },
        "Earnvids": {
          "35334-malep-18_otakuvid_sub": "https://otakuvid.online/embed/5259bm5hvovk",
          "35334-malep-18_otakuvid_sub_m3u8": null
        }
      },
      "dub": {},
      "hsub": {
        "HD-1": {
          "35334-malep-18_vibeplayer_hsub": "https://vibeplayer.site/2f7a83079d18abe7",
          "35334-malep-18_vibeplayer_hsub_m3u8": "https://vibeplayer.site/public/stream/2f7a83079d18abe7/master.m3u8"
        },
        "Earnvids": {
          "35334-malep-18_otakuvid_hsub": "https://otakuvid.online/embed/uej4ayd8am6l",
          "35334-malep-18_otakuvid_hsub_m3u8": null
        },
        "Doodstream": {
          "35334-malep-18_playmogo_hsub": "https://playmogo.com/e/96lm0bid6sjl",
          "35334-malep-18_playmogo_hsub_m3u8": null
        }
      }
    },
    {
      "episode_title": "The Melancholy of Schubert",
      "episode_url": "https://hianime.ad/watch/classicaloid-2/ep-19",
      "sub": {
        "HD-1": {
          "35334-malep-19_vibeplayer_sub": "https://vibeplayer.site/9f3e2c0013edfd34",
          "35334-malep-19_vibeplayer_sub_m3u8": "https://vibeplayer.site/public/stream/9f3e2c0013edfd34/master.m3u8"
        },
        "Earnvids": {
          "35334-malep-19_otakuvid_sub": "https://otakuvid.online/embed/nrt2s6cyc5ih",
          "35334-malep-19_otakuvid_sub_m3u8": null
        }
      },
      "dub": {},
      "hsub": {
        "HD-1": {
          "35334-malep-19_vibeplayer_hsub": "https://vibeplayer.site/ba7bb1cea5297a80",
          "35334-malep-19_vibeplayer_hsub_m3u8": "https://vibeplayer.site/public/stream/ba7bb1cea5297a80/master.m3u8"
        },
        "Earnvids": {
          "35334-malep-19_otakuvid_hsub": "https://otakuvid.online/embed/knylz1wo0m37",
          "35334-malep-19_otakuvid_hsub_m3u8": null
        },
        "Doodstream": {
          "35334-malep-19_playmogo_hsub": "https://playmogo.com/e/seewiqp142sj",
          "35334-malep-19_playmogo_hsub_m3u8": null
        }
      }
    },
    {
      "episode_title": "The Melancholy of Dovo-chan",
      "episode_url": "https://hianime.ad/watch/classicaloid-2/ep-20",
      "sub": {
        "HD-1": {
          "35334-malep-20_vibeplayer_sub": "https://vibeplayer.site/4fc2d0f770ad9eb5",
          "35334-malep-20_vibeplayer_sub_m3u8": "https://vibeplayer.site/public/stream/4fc2d0f770ad9eb5/master.m3u8"
        },
        "HD-2": {
          "35334-malep-20_vibeplayer_sub": "https://vibeplayer.site/ag08356769f57dc85724f1c7ec150c58774h",
          "35334-malep-20_vibeplayer_sub_m3u8": null
        },
        "Earnvids": {
          "35334-malep-20_otakuvid_sub": "https://otakuvid.online/embed/xi17s7c5y568",
          "35334-malep-20_otakuvid_sub_m3u8": null
        }
      },
      "dub": {},
      "hsub": {
        "HD-1": {
          "35334-malep-20_vibeplayer_hsub": "https://vibeplayer.site/26b551dd06b6d6bf",
          "35334-malep-20_vibeplayer_hsub_m3u8": "https://vibeplayer.site/public/stream/26b551dd06b6d6bf/master.m3u8"
        },
        "HD-2": {
          "35334-malep-20_vibeplayer_hsub": "https://vibeplayer.site/ag1bdae9969beb5c43cf2550ac4ddd6e7f4h",
          "35334-malep-20_vibeplayer_hsub_m3u8": null
        },
        "Earnvids": {
          "35334-malep-20_otakuvid_hsub": "https://otakuvid.online/embed/gif8slchua3c",
          "35334-malep-20_otakuvid_hsub_m3u8": null
        },
        "Doodstream": {
          "35334-malep-20_playmogo_hsub": "https://playmogo.com/e/3zv47zs958jl",
          "35334-malep-20_playmogo_hsub_m3u8": null
        }
      }
    },
    {
      "episode_title": "Chopin the Hero",
      "episode_url": "https://hianime.ad/watch/classicaloid-2/ep-21",
      "sub": {
        "HD-1": {
          "35334-malep-21_vibeplayer_sub": "https://vibeplayer.site/fa9de5898df027a6",
          "35334-malep-21_vibeplayer_sub_m3u8": "https://vibeplayer.site/public/stream/fa9de5898df027a6/master.m3u8"
        },
        "HD-2": {
          "35334-malep-21_vibeplayer_sub": "https://vibeplayer.site/ag6d2399be04e1e31f5e883c39f720e52a4h",
          "35334-malep-21_vibeplayer_sub_m3u8": null
        },
        "Earnvids": {
          "35334-malep-21_otakuvid_sub": "https://otakuvid.online/embed/mb8gb2p8b4vd",
          "35334-malep-21_otakuvid_sub_m3u8": null
        }
      },
      "dub": {},
      "hsub": {
        "HD-1": {
          "35334-malep-21_vibeplayer_hsub": "https://vibeplayer.site/10a087623f889edf",
          "35334-malep-21_vibeplayer_hsub_m3u8": "https://vibeplayer.site/public/stream/10a087623f889edf/master.m3u8"
        },
        "HD-2": {
          "35334-malep-21_vibeplayer_hsub": "https://vibeplayer.site/ag889a6537fe7bf194667accc1b28c31444h",
          "35334-malep-21_vibeplayer_hsub_m3u8": null
        },
        "Earnvids": {
          "35334-malep-21_otakuvid_hsub": "https://otakuvid.online/embed/7wwvnzu2gqya",
          "35334-malep-21_otakuvid_hsub_m3u8": null
        },
        "Doodstream": {
          "35334-malep-21_playmogo_hsub": "https://playmogo.com/e/5ub7xcj1aio8",
          "35334-malep-21_playmogo_hsub_m3u8": null
        }
      }
    },
    {
      "episode_title": "Bach, CLAKLA, Nibelungen",
      "episode_url": "https://hianime.ad/watch/classicaloid-2/ep-22",
      "sub": {
        "HD-1": {
          "35334-malep-22_vibeplayer_sub": "https://vibeplayer.site/3046208ef1966e77",
          "35334-malep-22_vibeplayer_sub_m3u8": "https://vibeplayer.site/public/stream/3046208ef1966e77/master.m3u8"
        },
        "HD-2": {
          "35334-malep-22_vibeplayer_sub": "https://vibeplayer.site/ag6d9c9c4911d3e760f43b5013541768814h",
          "35334-malep-22_vibeplayer_sub_m3u8": null
        },
        "Earnvids": {
          "35334-malep-22_otakuvid_sub": "https://otakuvid.online/embed/ui61ofbhx1gq",
          "35334-malep-22_otakuvid_sub_m3u8": null
        }
      },
      "dub": {},
      "hsub": {
        "HD-1": {
          "35334-malep-22_vibeplayer_hsub": "https://vibeplayer.site/12f196ad9689fac4",
          "35334-malep-22_vibeplayer_hsub_m3u8": "https://vibeplayer.site/public/stream/12f196ad9689fac4/master.m3u8"
        },
        "HD-2": {
          "35334-malep-22_vibeplayer_hsub": "https://vibeplayer.site/ag7d711eccd88f2fb5b1092a3ab853dcc04h",
          "35334-malep-22_vibeplayer_hsub_m3u8": null
        },
        "Earnvids": {
          "35334-malep-22_otakuvid_hsub": "https://otakuvid.online/embed/dt059pdty0bp",
          "35334-malep-22_otakuvid_hsub_m3u8": null
        },
        "Doodstream": {
          "35334-malep-22_playmogo_hsub": "https://playmogo.com/e/nyweahujc7rq",
          "35334-malep-22_playmogo_hsub_m3u8": null
        }
      }
    },
    {
      "episode_title": "A Long-Awaited Person Arrives, A Castle Is Built",
      "episode_url": "https://hianime.ad/watch/classicaloid-2/ep-23",
      "sub": {
        "HD-1": {
          "35334-malep-23_vibeplayer_sub": "https://vibeplayer.site/943716d5f100cc62",
          "35334-malep-23_vibeplayer_sub_m3u8": "https://vibeplayer.site/public/stream/943716d5f100cc62/master.m3u8"
        },
        "HD-2": {
          "35334-malep-23_vibeplayer_sub": "https://vibeplayer.site/ag9adc7b8c458fb52f3e1784dcda58d4aa4h",
          "35334-malep-23_vibeplayer_sub_m3u8": null
        },
        "Earnvids": {
          "35334-malep-23_otakuvid_sub": "https://otakuvid.online/embed/3o5b48j85f9t",
          "35334-malep-23_otakuvid_sub_m3u8": null
        }
      },
      "dub": {},
      "hsub": {
        "HD-1": {
          "35334-malep-23_vibeplayer_hsub": "https://vibeplayer.site/70d800696990fb0c",
          "35334-malep-23_vibeplayer_hsub_m3u8": "https://vibeplayer.site/public/stream/70d800696990fb0c/master.m3u8"
        },
        "HD-2": {
          "35334-malep-23_vibeplayer_hsub": "https://vibeplayer.site/ag6aff39120ddfff04ecca6410e5b4325f4h",
          "35334-malep-23_vibeplayer_hsub_m3u8": null
        },
        "Earnvids": {
          "35334-malep-23_otakuvid_hsub": "https://otakuvid.online/embed/0llc4ozjk7ug",
          "35334-malep-23_otakuvid_hsub_m3u8": null
        },
        "Doodstream": {
          "35334-malep-23_playmogo_hsub": "https://playmogo.com/e/c8xy887e6xdq",
          "35334-malep-23_playmogo_hsub_m3u8": null
        }
      }
    },
    {
      "episode_title": "Big Sister and Little Brother",
      "episode_url": "https://hianime.ad/watch/classicaloid-2/ep-24",
      "sub": {
        "HD-1": {
          "35334-malep-24_vibeplayer_sub": "https://vibeplayer.site/868fb6dffa07a24b",
          "35334-malep-24_vibeplayer_sub_m3u8": "https://vibeplayer.site/public/stream/868fb6dffa07a24b/master.m3u8"
        },
        "Earnvids": {
          "35334-malep-24_otakuvid_sub": "https://otakuvid.online/embed/koa5brezvu8d",
          "35334-malep-24_otakuvid_sub_m3u8": null
        }
      },
      "dub": {},
      "hsub": {
        "HD-1": {
          "35334-malep-24_vibeplayer_hsub": "https://vibeplayer.site/64ee4245d0f30b26",
          "35334-malep-24_vibeplayer_hsub_m3u8": "https://vibeplayer.site/public/stream/64ee4245d0f30b26/master.m3u8"
        },
        "Earnvids": {
          "35334-malep-24_otakuvid_hsub": "https://otakuvid.online/embed/j8xm7p6un2ti",
          "35334-malep-24_otakuvid_hsub_m3u8": null
        },
        "Doodstream": {
          "35334-malep-24_playmogo_hsub": "https://playmogo.com/e/518gnx24yuq5",
          "35334-malep-24_playmogo_hsub_m3u8": null
        }
      }
    },
    {
      "episode_title": "The Last ClassicaLoid",
      "episode_url": "https://hianime.ad/watch/classicaloid-2/ep-25",
      "sub": {
        "HD-1": {
          "35334-malep-25_vibeplayer_sub": "https://vibeplayer.site/9dbf5d69cb2bd66d",
          "35334-malep-25_vibeplayer_sub_m3u8": "https://vibeplayer.site/public/stream/9dbf5d69cb2bd66d/master.m3u8"
        },
        "HD-2": {
          "35334-malep-25_vibeplayer_sub": "https://vibeplayer.site/ag0a124f7a1abcbe0d6c4cd6c980f419874h",
          "35334-malep-25_vibeplayer_sub_m3u8": null
        },
        "Earnvids": {
          "35334-malep-25_otakuvid_sub": "https://otakuvid.online/embed/wdzam3mjzihf",
          "35334-malep-25_otakuvid_sub_m3u8": null
        }
      },
      "dub": {},
      "hsub": {
        "HD-1": {
          "35334-malep-25_vibeplayer_hsub": "https://vibeplayer.site/643eba147a743552",
          "35334-malep-25_vibeplayer_hsub_m3u8": "https://vibeplayer.site/public/stream/643eba147a743552/master.m3u8"
        },
        "HD-2": {
          "35334-malep-25_vibeplayer_hsub": "https://vibeplayer.site/ag0016c34fbdca3725a1b27852ceeab1844h",
          "35334-malep-25_vibeplayer_hsub_m3u8": null
        },
        "Earnvids": {
          "35334-malep-25_otakuvid_hsub": "https://otakuvid.online/embed/7d0q6jviaqnj",
          "35334-malep-25_otakuvid_hsub_m3u8": null
        },
        "Doodstream": {
          "35334-malep-25_playmogo_hsub": "https://playmogo.com/e/jzwjovarpfz8",
          "35334-malep-25_playmogo_hsub_m3u8": null
        }
      }
    }
  ]
}